<?xml version="1.0" encoding="utf-8" ?>
<Patch>   

                <!-- <Operation Class="PatchOperationAdd">
                    <xpath>Defs/ThingDef[defName="CA_WoodFiredTurbine"]</xpath>
                    <value>
                        <designatorDropdown>Ferny_WoodGenerators</designatorDropdown>
                    </value>
                </Operation>

                <Operation Class="PatchOperationAdd">
                    <xpath>Defs/ThingDef[defName="CA_ChemfuelTurbine"]</xpath>
                    <value>
                        <designatorDropdown>Ferny_ChemfuelGenerators</designatorDropdown>
                    </value>
                </Operation>


                <Operation Class="PatchOperationAdd">
                    <xpath>Defs/ThingDef[defName="CA_GasTurbine"]</xpath>
                    <value>
                        <designatorDropdown>Ferny_GasGenerators</designatorDropdown>
                    </value>
                </Operation> -->
</Patch>